[{"model": "admin.logentry", "pk": 1, "fields": {"action_time": "2023-04-15T08:43:40.246Z", "user": 1, "content_type": 16, "object_id": "1", "object_repr": "e33e7608c2264309a14db806912b50d02d1cb40c", "action_flag": 1, "change_message": "[{\"added\": {}}]"}}, {"model": "admin.logentry", "pk": 2, "fields": {"action_time": "2023-04-15T14:17:21.319Z", "user": 1, "content_type": 9, "object_id": "1", "object_repr": "name: тестовый, кг", "action_flag": 1, "change_message": "[{\"added\": {}}]"}}, {"model": "admin.logentry", "pk": 3, "fields": {"action_time": "2023-04-15T14:17:31.481Z", "user": 1, "content_type": 9, "object_id": "2", "object_repr": "name: тестовый 2, г", "action_flag": 1, "change_message": "[{\"added\": {}}]"}}, {"model": "admin.logentry", "pk": 4, "fields": {"action_time": "2023-04-15T14:19:18.704Z", "user": 1, "content_type": 10, "object_id": "1", "object_repr": "name: Завтрак", "action_flag": 1, "change_message": "[{\"added\": {}}]"}}, {"model": "admin.logentry", "pk": 5, "fields": {"action_time": "2023-04-15T15:13:17.605Z", "user": 1, "content_type": 9, "object_id": "3", "object_repr": "name: Картофель, г", "action_flag": 1, "change_message": "[{\"added\": {}}]"}}, {"model": "admin.logentry", "pk": 6, "fields": {"action_time": "2023-04-15T15:16:08.210Z", "user": 1, "content_type": 11, "object_id": "6", "object_repr": "name: картофель", "action_flag": 1, "change_message": "[{\"added\": {}}]"}}, {"model": "admin.logentry", "pk": 7, "fields": {"action_time": "2023-04-15T16:20:19.320Z", "user": 1, "content_type": 9, "object_id": "4", "object_repr": "name: тест1, 2", "action_flag": 1, "change_message": "[{\"added\": {}}]"}}, {"model": "admin.logentry", "pk": 8, "fields": {"action_time": "2023-04-15T16:20:48.890Z", "user": 1, "content_type": 11, "object_id": "10", "object_repr": "name: string", "action_flag": 2, "change_message": "[{\"changed\": {\"fields\": [\"\\u0418\\u043d\\u0433\\u0440\\u0435\\u0434\\u0438\\u0435\\u043d\\u0442\\u044b \\u0440\\u0435\\u0446\\u0435\\u043f\\u0442\\u0430\"]}}]"}}, {"model": "admin.logentry", "pk": 9, "fields": {"action_time": "2023-04-15T16:24:54.390Z", "user": 1, "content_type": 11, "object_id": "11", "object_repr": "name: Завтрак", "action_flag": 1, "change_message": "[{\"added\": {}}]"}}, {"model": "admin.logentry", "pk": 10, "fields": {"action_time": "2023-04-15T20:42:39.556Z", "user": 1, "content_type": 11, "object_id": "32", "object_repr": "name: string5", "action_flag": 3, "change_message": ""}}, {"model": "admin.logentry", "pk": 11, "fields": {"action_time": "2023-04-15T20:42:39.565Z", "user": 1, "content_type": 11, "object_id": "29", "object_repr": "name: string2222", "action_flag": 3, "change_message": ""}}, {"model": "admin.logentry", "pk": 12, "fields": {"action_time": "2023-04-15T20:42:39.569Z", "user": 1, "content_type": 11, "object_id": "28", "object_repr": "name: string2222", "action_flag": 3, "change_message": ""}}, {"model": "admin.logentry", "pk": 13, "fields": {"action_time": "2023-04-15T20:42:39.572Z", "user": 1, "content_type": 11, "object_id": "27", "object_repr": "name: string", "action_flag": 3, "change_message": ""}}, {"model": "admin.logentry", "pk": 14, "fields": {"action_time": "2023-04-15T20:42:39.575Z", "user": 1, "content_type": 11, "object_id": "26", "object_repr": "name: string", "action_flag": 3, "change_message": ""}}, {"model": "admin.logentry", "pk": 15, "fields": {"action_time": "2023-04-15T20:42:39.581Z", "user": 1, "content_type": 11, "object_id": "25", "object_repr": "name: string", "action_flag": 3, "change_message": ""}}, {"model": "admin.logentry", "pk": 16, "fields": {"action_time": "2023-04-15T20:42:39.583Z", "user": 1, "content_type": 11, "object_id": "24", "object_repr": "name: string5", "action_flag": 3, "change_message": ""}}, {"model": "admin.logentry", "pk": 17, "fields": {"action_time": "2023-04-15T20:42:39.585Z", "user": 1, "content_type": 11, "object_id": "23", "object_repr": "name: string5", "action_flag": 3, "change_message": ""}}, {"model": "admin.logentry", "pk": 18, "fields": {"action_time": "2023-04-15T20:42:39.587Z", "user": 1, "content_type": 11, "object_id": "22", "object_repr": "name: string5", "action_flag": 3, "change_message": ""}}, {"model": "admin.logentry", "pk": 19, "fields": {"action_time": "2023-04-15T20:42:39.589Z", "user": 1, "content_type": 11, "object_id": "21", "object_repr": "name: string5", "action_flag": 3, "change_message": ""}}, {"model": "admin.logentry", "pk": 20, "fields": {"action_time": "2023-04-15T20:42:39.591Z", "user": 1, "content_type": 11, "object_id": "20", "object_repr": "name: string5", "action_flag": 3, "change_message": ""}}, {"model": "admin.logentry", "pk": 21, "fields": {"action_time": "2023-04-15T20:42:39.593Z", "user": 1, "content_type": 11, "object_id": "19", "object_repr": "name: string5", "action_flag": 3, "change_message": ""}}, {"model": "admin.logentry", "pk": 22, "fields": {"action_time": "2023-04-15T20:42:39.595Z", "user": 1, "content_type": 11, "object_id": "18", "object_repr": "name: string1", "action_flag": 3, "change_message": ""}}, {"model": "admin.logentry", "pk": 23, "fields": {"action_time": "2023-04-15T20:42:39.597Z", "user": 1, "content_type": 11, "object_id": "17", "object_repr": "name: string1", "action_flag": 3, "change_message": ""}}, {"model": "admin.logentry", "pk": 24, "fields": {"action_time": "2023-04-15T20:42:39.600Z", "user": 1, "content_type": 11, "object_id": "16", "object_repr": "name: string1", "action_flag": 3, "change_message": ""}}, {"model": "admin.logentry", "pk": 25, "fields": {"action_time": "2023-04-15T20:42:39.602Z", "user": 1, "content_type": 11, "object_id": "15", "object_repr": "name: string", "action_flag": 3, "change_message": ""}}, {"model": "admin.logentry", "pk": 26, "fields": {"action_time": "2023-04-15T20:42:39.606Z", "user": 1, "content_type": 11, "object_id": "14", "object_repr": "name: string", "action_flag": 3, "change_message": ""}}, {"model": "admin.logentry", "pk": 27, "fields": {"action_time": "2023-04-15T20:42:39.610Z", "user": 1, "content_type": 11, "object_id": "13", "object_repr": "name: string", "action_flag": 3, "change_message": ""}}, {"model": "admin.logentry", "pk": 28, "fields": {"action_time": "2023-04-15T20:42:39.615Z", "user": 1, "content_type": 11, "object_id": "12", "object_repr": "name: string", "action_flag": 3, "change_message": ""}}, {"model": "admin.logentry", "pk": 29, "fields": {"action_time": "2023-04-15T20:42:39.617Z", "user": 1, "content_type": 11, "object_id": "11", "object_repr": "name: Завтрак", "action_flag": 3, "change_message": ""}}, {"model": "admin.logentry", "pk": 30, "fields": {"action_time": "2023-04-15T20:42:39.619Z", "user": 1, "content_type": 11, "object_id": "10", "object_repr": "name: string", "action_flag": 3, "change_message": ""}}, {"model": "admin.logentry", "pk": 31, "fields": {"action_time": "2023-04-15T20:42:39.646Z", "user": 1, "content_type": 11, "object_id": "9", "object_repr": "name: string", "action_flag": 3, "change_message": ""}}, {"model": "admin.logentry", "pk": 32, "fields": {"action_time": "2023-04-15T20:42:39.648Z", "user": 1, "content_type": 11, "object_id": "8", "object_repr": "name: string", "action_flag": 3, "change_message": ""}}, {"model": "admin.logentry", "pk": 33, "fields": {"action_time": "2023-04-15T20:42:39.650Z", "user": 1, "content_type": 11, "object_id": "7", "object_repr": "name: string", "action_flag": 3, "change_message": ""}}, {"model": "admin.logentry", "pk": 34, "fields": {"action_time": "2023-04-15T20:42:39.651Z", "user": 1, "content_type": 11, "object_id": "6", "object_repr": "name: картофель", "action_flag": 3, "change_message": ""}}, {"model": "admin.logentry", "pk": 35, "fields": {"action_time": "2023-04-15T20:42:39.652Z", "user": 1, "content_type": 11, "object_id": "5", "object_repr": "name: string", "action_flag": 3, "change_message": ""}}, {"model": "admin.logentry", "pk": 36, "fields": {"action_time": "2023-04-15T20:42:39.654Z", "user": 1, "content_type": 11, "object_id": "3", "object_repr": "name: string", "action_flag": 3, "change_message": ""}}, {"model": "auth.permission", "pk": 1, "fields": {"name": "Can add log entry", "content_type": 1, "codename": "add_logentry"}}, {"model": "auth.permission", "pk": 2, "fields": {"name": "Can change log entry", "content_type": 1, "codename": "change_logentry"}}, {"model": "auth.permission", "pk": 3, "fields": {"name": "Can delete log entry", "content_type": 1, "codename": "delete_logentry"}}, {"model": "auth.permission", "pk": 4, "fields": {"name": "Can view log entry", "content_type": 1, "codename": "view_logentry"}}, {"model": "auth.permission", "pk": 5, "fields": {"name": "Can add permission", "content_type": 2, "codename": "add_permission"}}, {"model": "auth.permission", "pk": 6, "fields": {"name": "Can change permission", "content_type": 2, "codename": "change_permission"}}, {"model": "auth.permission", "pk": 7, "fields": {"name": "Can delete permission", "content_type": 2, "codename": "delete_permission"}}, {"model": "auth.permission", "pk": 8, "fields": {"name": "Can view permission", "content_type": 2, "codename": "view_permission"}}, {"model": "auth.permission", "pk": 9, "fields": {"name": "Can add group", "content_type": 3, "codename": "add_group"}}, {"model": "auth.permission", "pk": 10, "fields": {"name": "Can change group", "content_type": 3, "codename": "change_group"}}, {"model": "auth.permission", "pk": 11, "fields": {"name": "Can delete group", "content_type": 3, "codename": "delete_group"}}, {"model": "auth.permission", "pk": 12, "fields": {"name": "Can view group", "content_type": 3, "codename": "view_group"}}, {"model": "auth.permission", "pk": 13, "fields": {"name": "Can add content type", "content_type": 5, "codename": "add_contenttype"}}, {"model": "auth.permission", "pk": 14, "fields": {"name": "Can change content type", "content_type": 5, "codename": "change_contenttype"}}, {"model": "auth.permission", "pk": 15, "fields": {"name": "Can delete content type", "content_type": 5, "codename": "delete_contenttype"}}, {"model": "auth.permission", "pk": 16, "fields": {"name": "Can view content type", "content_type": 5, "codename": "view_contenttype"}}, {"model": "auth.permission", "pk": 17, "fields": {"name": "Can add session", "content_type": 6, "codename": "add_session"}}, {"model": "auth.permission", "pk": 18, "fields": {"name": "Can change session", "content_type": 6, "codename": "change_session"}}, {"model": "auth.permission", "pk": 19, "fields": {"name": "Can delete session", "content_type": 6, "codename": "delete_session"}}, {"model": "auth.permission", "pk": 20, "fields": {"name": "Can view session", "content_type": 6, "codename": "view_session"}}, {"model": "auth.permission", "pk": 21, "fields": {"name": "Can add Token", "content_type": 15, "codename": "add_token"}}, {"model": "auth.permission", "pk": 22, "fields": {"name": "Can change Token", "content_type": 15, "codename": "change_token"}}, {"model": "auth.permission", "pk": 23, "fields": {"name": "Can delete Token", "content_type": 15, "codename": "delete_token"}}, {"model": "auth.permission", "pk": 24, "fields": {"name": "Can view Token", "content_type": 15, "codename": "view_token"}}, {"model": "auth.permission", "pk": 25, "fields": {"name": "Can add token", "content_type": 16, "codename": "add_tokenproxy"}}, {"model": "auth.permission", "pk": 26, "fields": {"name": "Can change token", "content_type": 16, "codename": "change_tokenproxy"}}, {"model": "auth.permission", "pk": 27, "fields": {"name": "Can delete token", "content_type": 16, "codename": "delete_tokenproxy"}}, {"model": "auth.permission", "pk": 28, "fields": {"name": "Can view token", "content_type": 16, "codename": "view_tokenproxy"}}, {"model": "auth.permission", "pk": 29, "fields": {"name": "Can add ('Пользователь',)", "content_type": 7, "codename": "add_userfoodgram"}}, {"model": "auth.permission", "pk": 30, "fields": {"name": "Can change ('Пользователь',)", "content_type": 7, "codename": "change_userfoodgram"}}, {"model": "auth.permission", "pk": 31, "fields": {"name": "Can delete ('Пользователь',)", "content_type": 7, "codename": "delete_userfoodgram"}}, {"model": "auth.permission", "pk": 32, "fields": {"name": "Can view ('Пользователь',)", "content_type": 7, "codename": "view_userfoodgram"}}, {"model": "auth.permission", "pk": 33, "fields": {"name": "Can add ('Подписка',)", "content_type": 8, "codename": "add_subscribe"}}, {"model": "auth.permission", "pk": 34, "fields": {"name": "Can change ('Подписка',)", "content_type": 8, "codename": "change_subscribe"}}, {"model": "auth.permission", "pk": 35, "fields": {"name": "Can delete ('Подписка',)", "content_type": 8, "codename": "delete_subscribe"}}, {"model": "auth.permission", "pk": 36, "fields": {"name": "Can view ('Подписка',)", "content_type": 8, "codename": "view_subscribe"}}, {"model": "auth.permission", "pk": 37, "fields": {"name": "Can add Ингредиент", "content_type": 9, "codename": "add_ingredient"}}, {"model": "auth.permission", "pk": 38, "fields": {"name": "Can change Ингредиент", "content_type": 9, "codename": "change_ingredient"}}, {"model": "auth.permission", "pk": 39, "fields": {"name": "Can delete Ингредиент", "content_type": 9, "codename": "delete_ingredient"}}, {"model": "auth.permission", "pk": 40, "fields": {"name": "Can view Ингредиент", "content_type": 9, "codename": "view_ingredient"}}, {"model": "auth.permission", "pk": 41, "fields": {"name": "Can add Тег", "content_type": 10, "codename": "add_tag"}}, {"model": "auth.permission", "pk": 42, "fields": {"name": "Can change Тег", "content_type": 10, "codename": "change_tag"}}, {"model": "auth.permission", "pk": 43, "fields": {"name": "Can delete Тег", "content_type": 10, "codename": "delete_tag"}}, {"model": "auth.permission", "pk": 44, "fields": {"name": "Can view Тег", "content_type": 10, "codename": "view_tag"}}, {"model": "auth.permission", "pk": 45, "fields": {"name": "Can add Рецепт", "content_type": 11, "codename": "add_recipes"}}, {"model": "auth.permission", "pk": 46, "fields": {"name": "Can change Рецепт", "content_type": 11, "codename": "change_recipes"}}, {"model": "auth.permission", "pk": 47, "fields": {"name": "Can delete Рецепт", "content_type": 11, "codename": "delete_recipes"}}, {"model": "auth.permission", "pk": 48, "fields": {"name": "Can view Рецепт", "content_type": 11, "codename": "view_recipes"}}, {"model": "auth.permission", "pk": 49, "fields": {"name": "Can add Избранное", "content_type": 12, "codename": "add_favorite"}}, {"model": "auth.permission", "pk": 50, "fields": {"name": "Can change Избранное", "content_type": 12, "codename": "change_favorite"}}, {"model": "auth.permission", "pk": 51, "fields": {"name": "Can delete Избранное", "content_type": 12, "codename": "delete_favorite"}}, {"model": "auth.permission", "pk": 52, "fields": {"name": "Can view Избранное", "content_type": 12, "codename": "view_favorite"}}, {"model": "auth.permission", "pk": 53, "fields": {"name": "Can add Корзина покупок", "content_type": 13, "codename": "add_carts"}}, {"model": "auth.permission", "pk": 54, "fields": {"name": "Can change Корзина покупок", "content_type": 13, "codename": "change_carts"}}, {"model": "auth.permission", "pk": 55, "fields": {"name": "Can delete Корзина покупок", "content_type": 13, "codename": "delete_carts"}}, {"model": "auth.permission", "pk": 56, "fields": {"name": "Can view Корзина покупок", "content_type": 13, "codename": "view_carts"}}, {"model": "auth.permission", "pk": 57, "fields": {"name": "Can add amount ingredients in recipes", "content_type": 14, "codename": "add_amountingredientsinrecipes"}}, {"model": "auth.permission", "pk": 58, "fields": {"name": "Can change amount ingredients in recipes", "content_type": 14, "codename": "change_amountingredientsinrecipes"}}, {"model": "auth.permission", "pk": 59, "fields": {"name": "Can delete amount ingredients in recipes", "content_type": 14, "codename": "delete_amountingredientsinrecipes"}}, {"model": "auth.permission", "pk": 60, "fields": {"name": "Can view amount ingredients in recipes", "content_type": 14, "codename": "view_amountingredientsinrecipes"}}, {"model": "contenttypes.contenttype", "pk": 1, "fields": {"app_label": "admin", "model": "logentry"}}, {"model": "contenttypes.contenttype", "pk": 2, "fields": {"app_label": "auth", "model": "permission"}}, {"model": "contenttypes.contenttype", "pk": 3, "fields": {"app_label": "auth", "model": "group"}}, {"model": "contenttypes.contenttype", "pk": 4, "fields": {"app_label": "auth", "model": "user"}}, {"model": "contenttypes.contenttype", "pk": 5, "fields": {"app_label": "contenttypes", "model": "contenttype"}}, {"model": "contenttypes.contenttype", "pk": 6, "fields": {"app_label": "sessions", "model": "session"}}, {"model": "contenttypes.contenttype", "pk": 7, "fields": {"app_label": "users", "model": "userfoodgram"}}, {"model": "contenttypes.contenttype", "pk": 8, "fields": {"app_label": "users", "model": "subscribe"}}, {"model": "contenttypes.contenttype", "pk": 9, "fields": {"app_label": "recipes", "model": "ingredient"}}, {"model": "contenttypes.contenttype", "pk": 10, "fields": {"app_label": "recipes", "model": "tag"}}, {"model": "contenttypes.contenttype", "pk": 11, "fields": {"app_label": "recipes", "model": "recipes"}}, {"model": "contenttypes.contenttype", "pk": 12, "fields": {"app_label": "recipes", "model": "favorite"}}, {"model": "contenttypes.contenttype", "pk": 13, "fields": {"app_label": "recipes", "model": "carts"}}, {"model": "contenttypes.contenttype", "pk": 14, "fields": {"app_label": "recipes", "model": "amountingredientsinrecipes"}}, {"model": "contenttypes.contenttype", "pk": 15, "fields": {"app_label": "authtoken", "model": "token"}}, {"model": "contenttypes.contenttype", "pk": 16, "fields": {"app_label": "authtoken", "model": "tokenproxy"}}, {"model": "sessions.session", "pk": "8gvk3wyyd6xpwl4bevo8z911e8lwj70d", "fields": {"session_data": ".eJxVjMsOwiAUBf-FtSHABSwu3fsNDfehVA0kpV0Z_12bdKHbMzPnpca8LmVcu8zjxOqkrDr8bpjpIXUDfM_11jS1uswT6k3RO-360lie5939Oyi5l28tEQafkkuWryge0VMIgEfDlj2RY2dtxETGBCaMhAOBOPAAJgEAq_cH5ho3vQ:1pnbVA:GAj_7I0Wcmi_TpY4Qb2fEbT90iYEAjV4HzJwpIAUT7w", "expire_date": "2023-04-29T08:43:20.712Z"}}, {"model": "authtoken.token", "pk": "4764857c21557cf4170ee81b7ca624175fb8d5cb", "fields": {"user": 2, "created": "2023-04-15T08:45:30.343Z"}}, {"model": "authtoken.token", "pk": "e33e7608c2264309a14db806912b50d02d1cb40c", "fields": {"user": 1, "created": "2023-04-15T08:43:40.239Z"}}, {"model": "users.userfoodgram", "pk": 1, "fields": {"last_login": "2023-04-15T08:43:20.708Z", "is_superuser": true, "username": "admin", "is_staff": true, "is_active": true, "date_joined": "2023-04-15T08:42:22.616Z", "password": "pbkdf2_sha256$390000$ONMM1lgLufz6ckmlVxBV1f$fsR6r8UdHWhRU0gRx8PPLW1C0+ERjgkAseV4qn3uWUM=", "first_name": "admin", "last_name": "admin1", "email": "admin@mail.ru", "groups": [], "user_permissions": []}}, {"model": "users.userfoodgram", "pk": 2, "fields": {"last_login": null, "is_superuser": false, "username": "vasya.pupkin", "is_staff": false, "is_active": true, "date_joined": "2023-04-15T08:44:32.479Z", "password": "pbkdf2_sha256$390000$Vv5wmnA5c2GEosgI6GMYxJ$dW+ZTJtBOoKtzyMH5nVpqNTZ38fAcZ3xStt5eMAsCR0=", "first_name": "Вася", "last_name": "Пупкин", "email": "vpupkin@yandex.ru", "groups": [], "user_permissions": []}}, {"model": "users.subscribe", "pk": 9, "fields": {"user": 1, "author": 2}}, {"model": "users.subscribe", "pk": 10, "fields": {"user": 1, "author": 1}}, {"model": "recipes.ingredient", "pk": 1, "fields": {"name": "тестовый", "measurement_unit": "кг"}}, {"model": "recipes.ingredient", "pk": 2, "fields": {"name": "тестовый 2", "measurement_unit": "г"}}, {"model": "recipes.ingredient", "pk": 3, "fields": {"name": "Картофель", "measurement_unit": "г"}}, {"model": "recipes.ingredient", "pk": 4, "fields": {"name": "тест1", "measurement_unit": "2"}}, {"model": "recipes.tag", "pk": 1, "fields": {"name": "Завтрак", "color": "#E26C2D", "slug": "breakfast"}}, {"model": "recipes.recipes", "pk": 33, "fields": {"author": 1, "name": "string", "image": "recipes/images/8507a5f6-bc3a-4694-b7f9-70d5b023e77a_7Bpf6jW.png", "text": "string", "cooking_time": 1, "pub_date": "2023-04-15T20:42:44.371Z", "ingredients": [], "tags": [1]}}, {"model": "recipes.recipes", "pk": 34, "fields": {"author": 1, "name": "string6", "image": "recipes/images/2593673d-48fe-4e63-9a9a-2f4ecd32db85.png", "text": "string1", "cooking_time": 1, "pub_date": "2023-04-16T20:06:04.059Z", "ingredients": [], "tags": [1]}}, {"model": "recipes.recipes", "pk": 35, "fields": {"author": 1, "name": "string6", "image": "recipes/images/eea4d987-f0b5-4c8d-9624-386cdc820c77.png", "text": "string1", "cooking_time": 1, "pub_date": "2023-04-16T20:06:42.480Z", "ingredients": [], "tags": [1]}}, {"model": "recipes.recipes", "pk": 36, "fields": {"author": 1, "name": "string6", "image": "recipes/images/535af2ae-d44b-4ecf-b983-8a1a62a98fc9.png", "text": "string1", "cooking_time": 1, "pub_date": "2023-04-16T20:16:20.104Z", "ingredients": [], "tags": [1]}}, {"model": "recipes.recipes", "pk": 37, "fields": {"author": 1, "name": "string6", "image": "recipes/images/0aa92159-042c-469f-9e05-0dddaba0ffbc.png", "text": "string1", "cooking_time": 1, "pub_date": "2023-04-16T20:16:33.284Z", "ingredients": [], "tags": [1]}}, {"model": "recipes.recipes", "pk": 38, "fields": {"author": 1, "name": "string77888", "image": "recipes/images/d7de122c-7211-4931-83ec-079078eb05ac.png", "text": "string1", "cooking_time": 1, "pub_date": "2023-04-16T20:18:19.088Z", "ingredients": [], "tags": [1]}}, {"model": "recipes.recipes", "pk": 40, "fields": {"author": 1, "name": "string77888", "image": "recipes/images/14cbe968-22c9-414e-b5c0-dd9dc5ce9039.png", "text": "string1", "cooking_time": 1, "pub_date": "2023-04-16T20:36:05.750Z", "ingredients": [], "tags": [1]}}, {"model": "recipes.recipes", "pk": 41, "fields": {"author": 1, "name": "string77888", "image": "recipes/images/d9d4627f-bd7a-498c-8e23-6c41178053f3.png", "text": "string1", "cooking_time": 1, "pub_date": "2023-04-16T20:36:38.764Z", "ingredients": [], "tags": [1]}}, {"model": "recipes.amountingredientsinrecipes", "pk": 26, "fields": {"recipe": 33, "ingredient": 1, "amount": 3}}, {"model": "recipes.amountingredientsinrecipes", "pk": 27, "fields": {"recipe": 34, "ingredient": 1, "amount": 3}}, {"model": "recipes.amountingredientsinrecipes", "pk": 28, "fields": {"recipe": 35, "ingredient": 1, "amount": 1}}, {"model": "recipes.amountingredientsinrecipes", "pk": 29, "fields": {"recipe": 36, "ingredient": 1, "amount": 1}}, {"model": "recipes.amountingredientsinrecipes", "pk": 30, "fields": {"recipe": 37, "ingredient": 1, "amount": 4}}, {"model": "recipes.amountingredientsinrecipes", "pk": 31, "fields": {"recipe": 38, "ingredient": 1, "amount": 4}}, {"model": "recipes.amountingredientsinrecipes", "pk": 32, "fields": {"recipe": 40, "ingredient": 1, "amount": 4}}, {"model": "recipes.amountingredientsinrecipes", "pk": 33, "fields": {"recipe": 41, "ingredient": 1, "amount": 4}}, {"model": "recipes.amountingredientsinrecipes", "pk": 34, "fields": {"recipe": 33, "ingredient": 1, "amount": 10}}]